well_architected_constructs/__init__.py
well_architected_constructs/api.py
well_architected_constructs/api_lambda.py
well_architected_constructs/api_lambda_dynamodb.py
well_architected_constructs/api_step_functions.py
well_architected_constructs/dynamodb_table.py
well_architected_constructs/lambda_function.py
well_architected_constructs/rest_api.py
well_architected_constructs/rest_api_sns.py
well_architected_constructs/sns_lambda.py
well_architected_constructs/web_application_firewall.py
well_architected_constructs/well_architected_construct.py
well_architected_constructs-0.1.2.dist-info/LICENSE
well_architected_constructs-0.1.2.dist-info/METADATA
well_architected_constructs-0.1.2.dist-info/WHEEL
well_architected_constructs-0.1.2.dist-info/top_level.txt
well_architected_constructs-0.1.2.dist-info/RECORD
